__init__.py
PPVD/__init__.py
PPVD/parsing.py
PPVD/style.py
PPVD/validation.py
PPVD-0.0.4.dist-info/LICENSE
PPVD-0.0.4.dist-info/METADATA
PPVD-0.0.4.dist-info/WHEEL
PPVD-0.0.4.dist-info/top_level.txt
PPVD-0.0.4.dist-info/RECORD
