Metadata-Version: 2.1
Name: PPVD
Version: 0.0.4
Summary: A collection parametrized parsing and validation decorators for python metaprogramming. Self-contained to avoid dependency clashing.
Author: Darik A. O'Neil
Maintainer: Darik A. O'Neil
License: MIT License
Keywords: python,parameterized,parsing,typing,validation,metaprogramming
Classifier: Development Status :: 4 - Beta
Classifier: Programming Language :: Python
Classifier: Operating System :: Microsoft :: Windows
Classifier: Operating System :: POSIX
Classifier: Operating System :: Unix
Classifier: Programming Language :: Python :: 3.7
Classifier: Programming Language :: Python :: 3.8
Classifier: Programming Language :: Python :: 3.9
Classifier: Programming Language :: Python :: 3.10
Requires-Python: <4,>=3.7
License-File: LICENSE
